{"2009":"8746","2010":"14195","2011":"20060","2012":"33513","2013":"49516","2014":"67060","2015":"84703","2016":"114549","2017":"122020","2018":"125027","2019":"132227","2020":"33457","mammal":"1441528","anthro":"1200685","female":"1087949","male":"981923","hi_res":"965807","solo":"924643","clothing":"766020","hair":"711185","breasts":"699764","penis":"654714","fur":"635679","duo":"625280","nude":"580658","genitals":"576423","bodily_fluids":"558909","canid":"535731","simple_background":"531546","canine":"527988","nipples":"482610","erection":"476819","video_games":"458221","clothed":"431524","genital_fluids":"424308","balls":"420431","sex":"411031","smile":"409415","pussy":"394493","blush":"391315","digital_media_(artwork)":"388614","open_mouth":"387760","looking_at_viewer":"374516","butt":"355053","penetration":"349513","tongue":"346281","text":"326569","cum":"309970","feral":"302756","big_breasts":"288353","horn":"287342","felid":"281426","nintendo":"278458","canis":"257718","equid":"255471","male/female":"254645","biped":"246573","absurd_res":"244145","white_body":"240331","anus":"232027","tongue_out":"231889","blue_eyes":"225735","english_text":"225518","wings":"223169","humanoid_genitalia":"216120","my_little_pony":"215465","male_penetrating":"213984","pokémon":"209019","pokémon_(species)":"207380","animal_genitalia":"199473","scalie":"199158","teeth":"197131","humanoid_penis":"192165","claws":"190438","group":"190319","standing":"189254","male/male":"187219","white_fur":"184419","white_background":"181403","vaginal":"180409","anal":"179314","friendship_is_magic":"177117","navel":"176432","monochrome":"172122","humanoid":"170951","cum_inside":"168989","muscular":"166863","topwear":"165587","fox":"164733","equine":"163337","lying":"163332","penile":"161747","spreading":"160166","eyes_closed":"158203","human":"157846","dragon":"154762","fingers":"154729","1:1":"148702","anal_penetration":"147482","green_eyes":"145546","toes":"145002","underwear":"143367","long_hair":"142854","outside":"140567","feline":"140357","comic":"140242","piercing":"138804","furniture":"138644","animal_penis":"137356","domestic_dog":"137344","brown_body":"137081","interspecies":"133885","oral":"132341","spread_legs":"131601","ambiguous_gender":"131543","sitting":"130103","vaginal_penetration":"129829","dialogue":"127455","looking_back":"126436","areola":"125342","feathers":"124113","tuft":"122752","blue_body":"121800","black_body":"121682","felis":"121414","<3":"120012","wolf":"119811","horse":"119503","brown_fur":"117946","eyewear":"115602","legwear":"114259","size_difference":"113098","hasbro":"112630","orgasm":"110329","young":"109905","leporid":"109200","lagomorph":"108071","bottomwear":"107745","solo_focus":"106953","narrowed_eyes":"106906","red_eyes":"106519","black_nose":"105507","thick_thighs":"104593","big_penis":"103434","huge_breasts":"102426","headgear":"101702","domestic_cat":"101012","paws":"99838","feathered_wings":"99651","shirt":"98155","grey_body":"97939","reptile":"97592","collar":"97228","multicolored_body":"96577","on_back":"96009","intersex":"95658","sweat":"95346","presenting":"94781","rabbit":"92554","blonde_hair":"92355","5_fingers":"91729","half-closed_eyes":"90876","fangs":"89470","black_fur":"89015","brown_hair":"88915","pantherine":"88236","wide_hips":"88151","saliva":"87470","headwear":"87013","yellow_body":"85955","black_hair":"85892","abs":"85710","big_butt":"84568","pony":"84036","muscular_male":"82767","knot":"82125","glasses":"81739","male_penetrated":"81233","ear_piercing":"80293","yellow_eyes":"79965","anthrofied":"79061","jewelry":"78881","pussy_juice":"78854","not_furry":"78339","blue_fur":"77841","bed":"77832","pecs":"77465","gynomorph":"76859","eyelashes":"76723","multicolored_hair":"76549","detailed_background":"76284","cutie_mark":"76256","vein":"75849","avian":"75463","ejaculation":"75291","hat":"75236","male_penetrating_male":"75124","unicorn":"74802","masturbation":"73730","markings":"73730","pawpads":"72162","non-mammal_breasts":"71879","grey_fur":"71722","barefoot":"71661","fellatio":"71599","purple_eyes":"71484","bound":"70998","inside":"70114","multicolored_fur":"70099","pose":"69895","bovid":"69555","signature":"69349","handwear":"68377","biceps":"68181","panties":"68176","footwear":"67868","licking":"67100","blue_hair":"66852","from_behind_position":"66710","gloves":"66527","cub":"66361","belly":"66191","anthro_on_anthro":"65976","animal_humanoid":"65968","disney":"65797","hybrid":"65527","cum_in_pussy":"65281","fan_character":"65106","membrane_(anatomy)":"62644","bottomless":"62468","topless":"62213","equine_penis":"62207","plant":"62085","4_toes":"61977","food":"61762","orange_body":"61711","overweight":"61538","precum":"61360","sketch":"60490","rodent":"60277","uncut":"59890","backsack":"59531","bdsm":"59166","white_hair":"58138","toe_claws":"58045","stripes":"57616","sex_toy":"57480","big_balls":"57036","purple_hair":"56908","clitoris":"56510","cum_in_ass":"56344","slightly_chubby":"56198","yellow_fur":"55846","membranous_wings":"55793","bulge":"55670","animated":"55612","raised_tail":"55422","hooves":"55363","marine":"55335","kneeling":"55311","one_eye_closed":"55259","sky":"55182","red_hair":"55126","canine_penis":"54922","all_fours":"54632","weapon":"54584","hyper":"54300","rear_view":"53897","group_sex":"53886","earth_pony":"53203","water":"52945","bird":"52750","eyebrows":"52551","portrait":"52473","purple_body":"52364","short_hair":"52351","tree":"52309","girly":"52255","cumshot":"52223","submissive":"52088","pink_hair":"51763","cleavage":"51696","holding_object":"51469","bondage":"50896","chest_tuft":"50644","two_tone_body":"50123","pterippus":"49819","scales":"49029","stockings":"48960","orange_fur":"48947","3d_(artwork)":"48390","feet":"47848","16:9":"47399","unknown_artist":"47315","speech_bubble":"46879","ursid":"46090","3_toes":"45970","looking_pleasured":"45840","tan_body":"45078","red_body":"44831","4:3":"44454","tears":"44365","japanese_text":"44361","front_view":"44142","pants":"44111","curvy_figure":"43960","swimwear":"43710","sonic_the_hedgehog_(series)":"43507","huge_penis":"43416","mammal_humanoid":"43391","two_tone_hair":"43319","faceless_male":"42878","voluptuous":"42852","fluffy":"42276","cum_in_mouth":"42184","female/female":"42008","greyscale":"41671","brown_eyes":"41571","digitigrade":"40823","presenting_hindquarters":"40666","pink_body":"40409","two_tone_fur":"40405","shoes":"40115","necklace":"40110","cum_on_face":"39984","bestiality":"39910","accessory":"39577","oral_penetration":"39430","thigh_highs":"39315","green_body":"39218","mostly_nude":"39108","pubes":"38991","seductive":"38943","black_and_white":"38806","on_top":"38695","female_penetrated":"38679","dildo":"38664","machine":"38641","domination":"38529","hindpaw":"38528","drooling":"38500","makeup":"38490","tiger":"38332","sheath":"37988","beak":"37771","forced":"37515","multicolored_tail":"37256","looking_at_another":"36887","caprine":"36794","partially_clothed":"36783","larger_male":"36624","sharp_teeth":"36372","grin":"36287","zootopia":"35757","tan_fur":"35735","armor":"35377","glowing":"35219","veiny_penis":"35155","skimpy":"34951","erect_nipples":"34001","4_fingers":"33898","tentacles":"33845","pillow":"33745","winged_unicorn":"33659","smaller_male":"33623","purple_fur":"33400","dripping":"32953","nipple_piercing":"32934","traditional_media_(artwork)":"32636","anthro_penetrated":"32510","penile_masturbation":"32317","mythology":"32087","grass":"31879","digital_drawing_(artwork)":"31686","kemono":"31509","cloud":"31448","arthropod":"31366","fish":"31343","alien":"31278","submissive_male":"31225","mustelid":"31181","alpha_channel":"30906","threesome":"30900","melee_weapon":"30879","spots":"30778","happy":"30535","inner_ear_fluff":"30515","low_res":"30385","lion":"30240","shorts":"30186","demon":"30172","big_muscles":"30087","disembodied_penis":"29975","fluffy_tail":"29949","after_sex":"29515","humanoid_hands":"29492","cum_on_penis":"29276","bikini":"28849","bovine":"28822","male_penetrating_female":"28700","facial_hair":"28692","pink_nose":"28589","whiskers":"28362","pokémorph":"28262","twilight_sparkle_(mlp)":"28245","human_on_anthro":"27939","armwear":"27793","grey_background":"27780","hand_on_breast":"27750","dress":"27601","pink_fur":"27521","cervid":"27447","handjob":"27428","transformation":"27306","kissing":"27177","digimon":"27105","skirt":"26925","murid":"26916","murine":"26765","robot":"26761","bent_over":"26717","digimon_(species)":"26693","on_bed":"26583","ribbons":"26579","hyper_genitalia":"26570","hand_on_butt":"26366","hair_accessory":"26339","conditional_dnp":"26314","wet":"26271","holidays":"26120","bedroom_eyes":"25860","messy":"25664","flaccid":"25564","legendary_pokémon":"25455","red_fur":"25434","long_ears":"25381","huge_balls":"25353","lips":"25334","side_view":"25307","black_penis":"25096","doggystyle":"25038","beverage":"24883","censored":"24829","anthro_penetrating":"24787","spikes":"24407","fully_clothed":"24375","big_belly":"24365","translated":"24303","night":"24264","side_boob":"24057","tattoo":"23808","fire":"23776","flower":"23769","undertale":"23762","rape":"23700","eeveelution":"23685","green_hair":"23443","soles":"23416","internal":"23397","bra":"23353","huge_butt":"23239","hyper_penis":"23141","open_smile":"23127","humanoid_pointy_ears":"23097","socks":"23043","dipstick_tail":"23004","boots":"22961","uniform":"22957","lizard":"22955","facial_piercing":"22782","crossgender":"22754","human_on_feral":"22701","vore":"22675","spitz":"22601","transparent_background":"22541","day":"22536","blue_feathers":"22519","seaside":"22361","body_hair":"22296","scar":"22273","judy_hopps":"22083","black_eyes":"22026","looking_down":"21996","rainbow_dash_(mlp)":"21868","fingering":"21866","cum_while_penetrated":"21857","big_dom_small_sub":"21754","athletic":"21718","abstract_background":"21691","chiropteran":"21655","abdominal_bulge":"21625","first_person_view":"21621","fluttershy_(mlp)":"21513","incest_(lore)":"21430","beach":"21344","small_breasts":"21121","age_difference":"21115","leash":"20939","overweight_male":"20891","torn_clothing":"20860","perineum":"20683","crossover":"20645","ponytail":"20624","shark":"20555","smaller_female":"20554","wink":"20429","freckles":"20343","nick_wilde":"20339","larger_female":"20260","belt":"20241","plantigrade":"20182","on_front":"20165","full-length_portrait":"20125","presenting_pussy":"20039","blue_skin":"20009","tight_clothing":"20002","forest":"19913","countershading":"19869","feral_on_feral":"19859","black_sclera":"19846","raised_leg":"19831","eulipotyphlan":"19769","blood":"19756","snout":"19698","mature_female":"19574","humor":"19543","bracelet":"19454","long_tail":"19296","angry":"19285","undressing":"19280","eye_contact":"19122","orange_eyes":"19100","glowing_eyes":"19095","gag":"19010","gesture":"18886","hedgehog":"18874","magic":"18854","pink_eyes":"18846","border":"18839","crown":"18833","felid_humanoid":"18779","ass_up":"18772","midriff":"18629","nipple_outline":"18626","vaginal_masturbation":"18617","pinkie_pie_(mlp)":"18564","ranged_weapon":"18533","poképhilia":"18476","on_side":"18430","high_heels":"18390","eyeshadow":"18299","cum_drip":"18266","5_toes":"18258","nordic_sled_dog":"18237","beard":"18236","orange_hair":"18233","mouse":"18226","sibling":"18219","rarity_(mlp)":"18194","lactating":"18163","5:4":"18159","lingerie":"18143","snake":"18134","hands-free":"18126","short_playtime":"18101","star":"18035","pink_nipples":"18021","partially_retracted_foreskin":"17999","source_filmmaker":"17988","mario_bros":"17915","surprise":"17879","animal_pussy":"17807","sword":"17777","translucent":"17749","cowgirl_position":"17682","intersex/female":"17678","gloves_(marking)":"17647","male_domination":"17632","crying":"17571","blizzard_entertainment":"17569","rubber":"17566","monster":"17562","shadow":"17521","feline_humanoid":"17481","procyonid":"17462","glistening":"17410","legs_up":"17319","sciurid":"17318","watermark":"17262","glans":"17209","pink_penis":"17114","cunnilingus":"17092","husky":"17058","crossdressing":"17027","cat_humanoid":"16784","3d_animation":"16711","scarf":"16659","raccoon":"16654","rainbow_hair":"16628","female_on_feral":"16584","insect":"16500","parent":"16417","double_penetration":"16408","webcomic":"16372","squish":"16362","!":"16361","facial_tuft":"16318","marsupial":"16317","hug":"16315","buckteeth":"16294","breast_grab":"16288","applejack_(mlp)":"16279","anthro_penetrating_anthro":"16268","inflation":"16266","hyper_breasts":"16244","dinosaur":"16234","fruit":"16209","no_sound":"16171","shota":"16139","alternate_species":"16063","cheek_tuft":"16054","toony":"16011","hyper_balls":"16001","cattle":"15982","half-erect":"15981","penis_lick":"15969","flat_chested":"15965","rope":"15916","pinup":"15904","url":"15821","leg_markings":"15649","clenched_teeth":"15643","multi_tail":"15638","gynomorph/female":"15616","<3_eyes":"15539","slit_pupils":"15510","submissive_female":"15504","mask":"15503","antlers":"15488","2d_animation":"15477","nose_piercing":"15470","princess_celestia_(mlp)":"15461","animal_crossing":"15405","star_fox":"15364","breath":"15346","foreskin":"15342","necktie":"15293","princess_luna_(mlp)":"15242","amber_eyes":"15236","hand_on_hip":"15174","tank_top":"15153","muscular_female":"15152","cum_on_breasts":"15114","lutrine":"15078","excessive_cum":"15074","warcraft":"15009","slit":"14959","jacket":"14888","public":"14869","bite":"14822","camel_toe":"14801","romantic_ambiance":"14801","moon":"14800","vehicle":"14797","mane":"14774","chair":"14752","grey_hair":"14686","gun":"14664","tapering_penis":"14611","sleeping":"14602","sofa":"14571","anatomically_correct":"14569","elbow_gloves":"14569","socks_(marking)":"14534","missionary_position":"14508","were":"14503","widescreen":"14453","female_focus":"14410","featureless_crotch":"14322","hyaenid":"14309","human_penetrating":"14290","cartoon_network":"14285","head_markings":"14275","bone":"14261","mythological_avian":"14195","thick_penis":"14179","striped_body":"14165","restrained":"14160","facial_markings":"14117","canid_humanoid":"14105","book":"14098","western_dragon":"14060","pastoral_dog":"14059","gradient_background":"14044","canine_humanoid":"14031","macro":"13925","disembodied_hand":"13903","gagged":"13882","window":"13863","elemental_creature":"13858","mephitid":"13854","herding_dog":"13839","cum_on_self":"13812","lipstick":"13721","ahegao":"13712","cum_on_butt":"13694","intersex/male":"13679","chain":"13670","edit":"13651","intersex_penetrating":"13637","breast_squish":"13590","titfuck":"13574","skunk":"13530","butt_grab":"13505","close-up":"13499","bow":"13491","female_domination":"13436","hoodie":"13436","toying_self":"13399","blue_background":"13350","armpit_hair":"13332","foot_fetish":"13303","cum_string":"13201","yellow_sclera":"13175","translation_request":"13172","embarrassed":"13156","sound_effects":"13110","thong":"13108","not_furry_focus":"13083","bedroom":"13018","herm":"12982","musteline":"12981","goggles":"12931","christmas":"12921","five_nights_at_freddy's":"12917","spotted_body":"12887","renamon":"12847","werecanid":"12844","loli":"12821","clothing_lift":"12807","pregnant":"12759","holding_weapon":"12723","romantic_couple":"12719","loop":"12716","fondling":"12701","green_skin":"12670","phone":"12604","white_skin":"12587","bell":"12542","duo_focus":"12542","spread_pussy":"12512","lucario":"12497","alcohol":"12468","humanoid_feet":"12459","licking_lips":"12390","crouching":"12361","ambiguous_penetration":"12350","genital_slit":"12302","low-angle_view":"12278","self_lick":"12225","green_fur":"12208","gaping":"12171","striped_fur":"12151","?":"12133","short_stack":"12112","anthro_on_feral":"12107","hair_ribbon":"12064","looking_up":"12063","pink_tongue":"12027","long_tongue":"12024","three-quarter_portrait":"12000","white_feathers":"11982","male_on_feral":"11972","multi_genitalia":"11972","fingerless_gloves":"11941","multicolored_ears":"11921","sand":"11915","boss_monster":"11877","gynomorph_penetrating":"11853","obese":"11851","white_balls":"11780","line_art":"11725","cum_inflation":"11706","featureless_breasts":"11667","presenting_anus":"11624","costume":"11615","cum_leaking":"11584","puffy_anus":"11549","black_nipples":"11538","spotted_fur":"11527","overweight_female":"11512","semi-anthro":"11491","helmet":"11473","sunglasses":"11460","yellow_feathers":"11436","leaking":"11409","nails":"11396","raised_arm":"11394","crocodilian":"11386","3_fingers":"11356","unknown_species":"11345","one_eye_obstructed":"11292","child":"11246","flora_fauna":"11237","human_focus":"11209","multi_penis":"11204","hair_over_eye":"11189","brother":"11188","patreon":"11183","hands_behind_back":"11180","goat":"11171","big_ears":"11158","furred_dragon":"11157","light":"11154","sister":"11153","the_legend_of_zelda":"11145","frown":"11143","moobs":"11127","heterochromia":"11118","fin":"11107","hair_bow":"11060","cute_fangs":"11057","ball_gag":"11012","primate":"10995","rimming":"10991","blue_penis":"10989","sweater":"10975","snow":"10957","male/ambiguous":"10924","bow_tie":"10913","two_tone_tail":"10900","retracted_foreskin":"10895","genital_piercing":"10868","dipstick_ears":"10819","milk":"10783","parent_and_child":"10770","fennec":"10756","mother":"10721","foot_play":"10719","model_sheet":"10706","capcom":"10694","animatronic":"10670","bedding":"10655","quadruped":"10647","table":"10594","anatomically_correct_genitalia":"10583","human_on_humanoid":"10517","anal_masturbation":"10515","pants_down":"10513","teats":"10512","gryphon":"10505","moan":"10494","straddling":"10484","cum_on_ground":"10482","spotted_hyena":"10477","neck_tuft":"10474","what":"10376","ailurid":"10331","leopard":"10279","towel":"10256","medial_ring":"10234","royalty":"10147","equine_pussy":"10132","tail_tuft":"10103","riot_games":"10079","league_of_legends":"10078","musclegut":"10074","cheetah":"10059","red_panda":"10051","multi_limb":"10038","colored":"10017","suina":"9991","male_pov":"9936","white_tail":"9935","antennae_(anatomy)":"9929","cum_on_balls":"9922","brown_nose":"9921","asian_mythology":"9881","elf":"9856","sweatdrop":"9834","east_asian_mythology":"9834","cum_on_chest":"9828","open_shirt":"9823","dock":"9821","sound":"9817","loincloth":"9790","flying":"9781","sexual_barrier_device":"9757","shackles":"9754","condom":"9752","square_enix":"9716","sheep":"9701","tree_squirrel":"9694","eye_patch":"9589","looking_away":"9589","human_penetrating_anthro":"9572","tokyo_afterschool_summoners":"9527","hands_behind_head":"9490","bandage":"9472","werecanine":"9460","sonic_the_hedgehog":"9439","head_tuft":"9386","urine":"9383","black_skin":"9371","rock":"9368","nose_ring":"9363","mind_control":"9361","smoking":"9253","sea":"9224","white_clothing":"9213","werewolf":"9187","pivoted_ears":"9186","snow_leopard":"9168","smirk":"9119","vibrator":"9109","asian_clothing":"9097","braided_hair":"9091","purple_skin":"9091","lynx":"9086","black_clothing":"9075","fucked_silly":"9068","east_asian_clothing":"9055","hand_on_head":"9026","suid":"9025","feral_penetrating":"9024","dark_skin":"9023","frame_by_frame":"8989","source_request":"8986","spike_(mlp)":"8939","sucking":"8883","graphite_(artwork)":"8856","giant_panda":"8852","pikachu":"8845","reclining":"8842","undead":"8836","pencil_(artwork)":"8819","motion_lines":"8811","younger_male":"8809","foot_focus":"8806","rat":"8792","pattern_clothing":"8759","nipple_fetish":"8749","nipple_play":"8723","shirt_lift":"8711","mollusk":"8702","knotting":"8700","sus_(pig)":"8696","thick_tail":"8684","orgasm_face":"8669","cosplay":"8666","monster_girl_(genre)":"8654","flash":"8650","floppy_ears":"8612","spirit":"8601","gynomorph/male":"8565","suit":"8538","amphibian":"8536","cum_on_tongue":"8518","jackal":"8501","macropod":"8491","3:4":"8480","leg_grab":"8447","wood":"8443","rouge_the_bat":"8436","candy":"8413","cum_on_leg":"8405","choker":"8404","penile_spines":"8403","naughty_face":"8394","ear_ring":"8388","son":"8379","ursine":"8370","cape":"8311","cum_on_stomach":"8285","biting_lip":"8282","cutaway":"8273","huge_muscles":"8262","smoke":"8256","reverse_cowgirl_position":"8244","plump_labia":"8240","zebra":"8228","green_scales":"8219","vaginal_fingering":"8211","micro":"8179","nature":"8170","japanese_clothing":"8155","grey_skin":"8148","human_penetrated":"8142","alternate_color":"8138","fully_sheathed":"8060","furgonomics":"8050","pink_background":"8039","blue_nose":"8032","fox_humanoid":"8018","koopa":"8018","story":"8017","bandanna":"8017","theropod":"8012","slim":"8011","tools":"7989","changeling":"7975","kangaroo":"7967","diaper":"7966","hand_behind_head":"7959","bethesda_softworks":"7957","blue_scales":"7947","meme":"7929","cup":"7928","white_border":"7900","spitroast":"7884","under_boob":"7873","european_mythology":"7843","building":"7819","ring":"7800","purple_background":"7798","16:10":"7777","fishnet":"7748","clothing_aside":"7746","leaning":"7686","small_dom_big_sub":"7685","miles_prower":"7684","gem":"7680","final_fantasy":"7650","grope":"7645","striped_clothing":"7635","big_eyes":"7624","taur":"7607","egg":"7584","blue_nipples":"7580","multi_arm":"7578","halloween":"7577","penis_tip":"7566","high-angle_view":"7565","self_bite":"7565","covering":"7555","...":"7531","tentacle_sex":"7511","gangbang":"7501","looking_aside":"7500","spread_butt":"7489","black_claws":"7484","insect_wings":"7476","feral_penetrated":"7464","red_skin":"7446","biting_own_lip":"7433","german_shepherd":"7411","partially_submerged":"7398","eating":"7383","greek_mythology":"7369","deep_throat":"7338"}